restep/__init__.py
restep/document_reader.py
restep/generator.py
restep/restep.py
restep/retriever.py
restep-0.0.3.dist-info/LICENSE
restep-0.0.3.dist-info/METADATA
restep-0.0.3.dist-info/WHEEL
restep-0.0.3.dist-info/top_level.txt
restep-0.0.3.dist-info/RECORD
