Metadata-Version: 2.1
Name: restep
Version: 0.0.3
Summary: Reason-based RAG for Early-Stage Developers for Community-based Prospecting (RE-STEP)
Author: Charles Alba
Author-email: alba@wustl.edu
Keywords: Retrieval-augmented generation,Renewable-energy prospecting technologies,Built-environment decision-support systems
Classifier: Development Status :: 1 - Planning
Classifier: Intended Audience :: Science/Research
Classifier: Programming Language :: Python :: 3
Classifier: Operating System :: Unix
Classifier: Operating System :: MacOS :: MacOS X
Classifier: Operating System :: Microsoft :: Windows
Requires-Python: >=3.8
License-File: LICENSE
Requires-Dist: requests
Requires-Dist: PyPDF2
Requires-Dist: python-docx
Requires-Dist: langchain>=0.2
Requires-Dist: langchain-community>=0.2
Requires-Dist: tqdm
Requires-Dist: transformers
Requires-Dist: torch
Requires-Dist: accelerate
Requires-Dist: safetensors
Requires-Dist: sentencepiece
Requires-Dist: bitsandbytes
